plover_python_dictionary_lib.py
plover_python_dictionary_lib/__init__.py
plover_python_dictionary_lib/plover_python_dictionary_lib.py
plover_python_dictionary_lib/py.typed
plover_python_dictionary_lib-0.5.0.dist-info/LICENSE
plover_python_dictionary_lib-0.5.0.dist-info/METADATA
plover_python_dictionary_lib-0.5.0.dist-info/WHEEL
plover_python_dictionary_lib-0.5.0.dist-info/top_level.txt
plover_python_dictionary_lib-0.5.0.dist-info/zip-safe
plover_python_dictionary_lib-0.5.0.dist-info/RECORD
