Metadata-Version: 2.1
Name: plover_python_dictionary_lib
Version: 0.5.0
Summary: Library for writing Python dictionary for Plover, and generating JSON dictionary file from Python dictionary.
Home-page: https://github.com/user202729/plover-python-dictionary-lib
Author: user202729
License: GNU General Public License v3 or later (GPLv3+)
Keywords: plover
Classifier: Environment :: Plugins
Classifier: License :: OSI Approved :: GNU General Public License v3 or later (GPLv3+)
Classifier: Operating System :: OS Independent
Classifier: Programming Language :: Python :: 3
License-File: LICENSE
Requires-Dist: plover-stroke>=0.4.0
